[
    {
        "value": 0,
        "text": "全选",
        "index": 1,
        "defaultselect": null
    },
    {
        "value": 1,
        "text": "无",
        "index": 2,
        "defaultselect": null
    },
    {
        "value": 2,
        "text": "闭经",
        "index": 3,
        "defaultselect": null
    },
    {
        "value": 3,
        "text": "月经稀发",
        "index": 4,
        "defaultselect": null
    },
    {
        "value": 4,
        "text": "腹痛",
        "index": 5,
        "defaultselect": null
    },
    {
        "value": 5,
        "text": "头痛",
        "index": 6,
        "defaultselect": null
    }
]